{
  "qualified_handle": "web/fix-login",
  "repo": "web",
  "title": "Fix login",
  "branch": "ajax/fix-login",
  "base_branch": "main",
  "worktree_path": "/repo/web__worktrees/ajax-fix-login",
  "tmux_session": "ajax-web-fix-login",
  "lifecycle": "Reviewable",
  "agent": "Codex",
  "agent_status": "Waiting",
  "status": "waiting",
  "status_explanation": "Waiting for approval",
  "runtime_observation_error": null,
  "actions": [
    {
      "action": "resume",
      "label": "Resume",
      "destructive": false,
      "confirmation_required": false
    },
    {
      "action": "ship",
      "label": "Ship",
      "destructive": false,
      "confirmation_required": false
    },
    {
      "action": "drop",
      "label": "Drop",
      "destructive": true,
      "confirmation_required": true
    }
  ],
  "live_status_kind": "WaitingForApproval",
  "live_status_summary": "waiting for review",
  "agent_activity": "waiting for review",
  "git": null,
  "tmux": null,
  "annotations": [
    "Annotation { kind: NeedsMe, severity: 1, evidence: LiveStatus(WaitingForApproval), suggests: Resume }",
    "Annotation { kind: Reviewable, severity: 3, evidence: Lifecycle(Reviewable), suggests: Review }"
  ],
  "created_unix_secs": 1700000000,
  "last_activity_unix_secs": 1700001000,
  "agent_attempts": [
    {
      "started_unix_secs": 1700000000,
      "completed_unix_secs": 1700001000,
      "outcome": "Done"
    }
  ]
}
